arxiv_auto_crawler/__init__.py
arxiv_auto_crawler/daily_crawl.py
arxiv_auto_crawler/download_file.py
arxiv_auto_crawler-0.0.6.dist-info/LICENSE
arxiv_auto_crawler-0.0.6.dist-info/METADATA
arxiv_auto_crawler-0.0.6.dist-info/WHEEL
arxiv_auto_crawler-0.0.6.dist-info/top_level.txt
arxiv_auto_crawler-0.0.6.dist-info/RECORD
