Metadata-Version: 2.1
Name: arxiv-auto-crawler
Version: 0.0.6
Summary: Used for crawling arxiv papers automatically.
Home-page: https://github.com/AI-confused/arxiv_scrawl
Author: black_tears
Author-email: 21860437@zju.edu.cn
License: UNKNOWN
Project-URL: Bug Tracker, https://github.com/AI-confused/arxiv_scrawl/issues
Platform: UNKNOWN
Classifier: Programming Language :: Python :: 3
Classifier: License :: OSI Approved :: MIT License
Classifier: Operating System :: OS Independent
Requires-Python: >=3.6
License-File: LICENSE
